LICENSE
MANIFEST.in
README.md
setup.py
sine/__init__.py
sine.utils.egg-info/PKG-INFO
sine.utils.egg-info/SOURCES.txt
sine.utils.egg-info/dependency_links.txt
sine.utils.egg-info/namespace_packages.txt
sine.utils.egg-info/requires.txt
sine.utils.egg-info/top_level.txt
sine/utils/__init__.py
sine/utils/__meta__.py
sine/utils/application.py
sine/utils/event.py
sine/utils/func.py
sine/utils/path.py
sine/utils/properties.py
sine/utils/storage.py
sine/utils/testEvent.py
sine/utils/testPath.py
sine/utils/testProperties.py
sine/utils/testStorage.py
sine/utils/testThreads.py
sine/utils/threads.py